flare_pp/_C_flare.cpython-36m-darwin.so
flare_pp/__init__.py
flare_pp/parsers.py
flare_pp/sparse_gp.py
flare_pp/sparse_gp_calculator.py
tests/__init__.py
tests/get_sgp.py
tests/test_lammps.py
tests/test_parse.py
tests/test_sparse_gp.py
tests/test_tutorial.py
flare_pp-0.1.1.dist-info/LICENSE
flare_pp-0.1.1.dist-info/METADATA
flare_pp-0.1.1.dist-info/WHEEL
flare_pp-0.1.1.dist-info/top_level.txt
flare_pp-0.1.1.dist-info/RECORD
