Metadata-Version: 2.1
Name: flare-pp
Version: 0.1.1
Summary: Many-body extension of the flare code
Home-page: https://github.com/mir-group/flare_pp
Author: Materials Intelligence Research
Author-email: mir@g.harvard.edu
License: MIT
Platform: UNKNOWN
Classifier: License :: OSI Approved :: MIT License
Classifier: Topic :: Scientific/Engineering :: Physics
Classifier: Topic :: Scientific/Engineering :: Artificial Intelligence
Classifier: Development Status :: 4 - Beta
Requires-Python: >=3.6
Requires-Dist: cmake (>=3.14.5)
Requires-Dist: mir-flare
Requires-Dist: jupyter
Requires-Dist: nbconvert
